verifyauth/__init__.py
verifyauth/decorator.py
verifyauth/response_handler.py
verifyauth/util.py
verifyauth-0.1.31.dist-info/METADATA
verifyauth-0.1.31.dist-info/WHEEL
verifyauth-0.1.31.dist-info/top_level.txt
verifyauth-0.1.31.dist-info/RECORD
