Metadata-Version: 2.1
Name: verifyauth
Version: 0.1.31
Summary: A decorator for FastAPI to verify authentication and authorization via an external service.
Home-page: 
Author: Cosme Sousa
Author-email: 
Classifier: Programming Language :: Python :: 3
Classifier: License :: OSI Approved :: MIT License
Classifier: Operating System :: OS Independent
Requires-Python: >=3.6
Requires-Dist: requests
Requires-Dist: fastapi
